log_decor/__init__.py
log_decor/add.py
log_decor/func.py
log_decor/info.py
log_decor/msg.py
log_decor-2.0.5.dist-info/LICENSE
log_decor-2.0.5.dist-info/METADATA
log_decor-2.0.5.dist-info/WHEEL
log_decor-2.0.5.dist-info/RECORD
