Metadata-Version: 2.1
Name: log-decor
Version: 2.0.5
Summary: Logging decorators for functions and methods.
License: MIT
Keywords: logging,decorator,OOP
Author: Bernardo Paulsen
Author-email: paulsen.bernardo@gmail.com
Requires-Python: >=3.10,<4.0
Classifier: License :: OSI Approved :: MIT License
Classifier: Programming Language :: Python :: 3
Classifier: Programming Language :: Python :: 3.10
Classifier: Programming Language :: Python :: 3.11
Project-URL: Documentation, https://bernardopaulsen.github.io/log_decor/
Project-URL: GitHub, https://github.com/bernardopaulsen/log_decor
